{
    "домашний": "casero",
    "Париже": "París",
    "культурный": "cultural",
    "Зоя": "Zoya",
    "ответьте": "responda",
    "летний": "veraniego",
    "труднее": "más difícil",
    "У": "en",
    "дороже": "más caro",
    "театром": "teatro",
    "сейчас": "ahora",
    "заканчивает": "termina",
    "в": "en",
    "Мою": "mi",
    "назад": "atrás",
    "по": "por",
    "экстремальным": "extremo",
    "какую": "cuál",
    "моему": "mi",
    "любите": "amas",
    "легче": "más fácil",
    "занимаюсь": "me ocupo",
    "городе": "ciudad",
    "твоей": "tu",
    "Испанию": "España",
    "А": "y",
    "когда": "cuándo",
    "учится": "estudia",
    "будущее": "futuro",
    "гаджеты": "gadgets",
    "свой": "mi",
    "время": "tiempo",
    "Он": "él",
    "интернет": "internet",
    "плачу": "pago",
    "рук": "manos",
    "только": "sólo",
    "этот": "este",
    "Кто": "quién",
    "принимает": "acepta",
    "поехать": "ir",
    "потому": "porque",
    "хотели": "querían",
    "года": "años",
    "отпуске": "vacaciones",
    "блюда": "platos",
    "Москва": "Moscú",
    "живет": "vive",
    "лет": "años",
    "последний": "último",
    "заказ": "pedido",
    "виды": "vistas",
    "вас": "usted",
    "давно": "hace mucho",
    "какой": "cuál",
    "Брат": "hermano",
    "пойти": "ir",
    "там": "allí",
    "живут": "viven",
    "да": "sí",
    "ездить": "viajar",
    "официант": "camarero",
    "спонтанно": "espontáneamente",
    "спросом": "demanda",
    "знаете": "sabes",
    "езжу": "viajo",
    "ты": "tú",
    "отеле": "hotel",
    "дом": "casa",
    "Задание": "tarea",
    "Где": "dónde",
    "мама": "madre",
    "институт": "instituto",
    "занимаетесь": "te ocupas",
    "было": "fue",
    "поступать": "ingresar",
    "больше": "más",
    "стране": "país",
    "работать": "trabajar",
    "до": "hasta",
    "Сколько": "cuánto",
    "рынке": "mercado",
    "командировки": "viajes de trabajo",
    "Да": "sí",
    "чем": "que",
    "сколько": "cuánto",
    "у": "en",
    "месте": "lugar",
    "сестре": "hermana",
    "путешествия": "viajes",
    "ходит": "va",
    "магазине": "tienda",
    "молоком": "leche",
    "а": "y",
    "планы": "planes",
    "Диалог": "diálogo",
    "Россией": "Rusia",
    "то": "entonces",
    "самообслуживание": "autoservicio",
    "найти": "encontrar",
    "семье": "familia",
    "онлайн": "en línea",
    "был": "fue",
    "спортом": "deporte",
    "кафе": "café",
    "своём": "mi",
    "хотите": "quieres",
    "Зеландия": "Zelanda",
    "Какое": "cuál",
    "транспорт": "transporte",
    "путешествовать": "viajar",
    "Мехико": "México",
    "Вы": "usted",
    "перед": "antes de",
    "Кому": "a quién",
    "составляете": "creas",
    "есть": "hay",
    "этом": "esto",
    "без": "sin",
    "точно": "exactamente",
    "нибудь": "cualquier",
    "отпуск": "vacaciones",
    "следующие": "siguientes",
    "занимается": "se ocupa",
    "ночевать": "pasar la noche",
    "Когда": "cuándo",
    "обычном": "normal",
    "мне": "a mí",
    "делать": "hacer",
    "Ты": "tú",
    "Или": "o",
    "экскурсии": "excursiones",
    "языке": "idioma",
    "блюдо": "plato",
    "брат": "hermano",
    "Канада": "Canadá",
    "раз": "vez",
    "о": "sobre",
    "маму": "mamá",
    "они": "ellos",
    "научный": "científico",
    "во": "en",
    "музеи": "museos",
    "регулярно": "regularmente",
    "русском": "ruso",
    "ваше": "tu",
    "Сейчас": "ahora",
    "национальные": "nacionales",
    "природе": "naturaleza",
    "работает": "trabaja",
    "другу": "amigo"
}
